makelove/__init__.py
makelove/__main__.py
makelove/config.py
makelove/filelist.py
makelove/hooks.py
makelove/jsonfile.py
makelove/linux.py
makelove/lovejs.py
makelove/macos.py
makelove/makelove.py
makelove/util.py
makelove/validators.py
makelove/windows.py
makelove-0.0.13.dist-info/LICENSE
makelove-0.0.13.dist-info/METADATA
makelove-0.0.13.dist-info/WHEEL
makelove-0.0.13.dist-info/entry_points.txt
makelove-0.0.13.dist-info/top_level.txt
makelove-0.0.13.dist-info/RECORD
