Metadata-Version: 2.1
Name: makelove
Version: 0.0.13
Summary: A packaging tool for [löve](https://love2d.org) games
Home-page: https://github.com/pfirsich/makelove
Author: Joel Schumacher
Author-email: joelschum@gmail.com
License: UNKNOWN
Platform: UNKNOWN
Classifier: Programming Language :: Python :: 3
Classifier: License :: OSI Approved :: MIT License
Classifier: Operating System :: OS Independent
Requires-Python: >=3.7
License-File: LICENSE
Requires-Dist: Pillow (>=7.0)
Requires-Dist: appdirs (>=1.4.3)
Requires-Dist: toml (>=0.10)
